helperJS/__init__.py
HelperJS-1.0.dist-info/METADATA
HelperJS-1.0.dist-info/WHEEL
HelperJS-1.0.dist-info/top_level.txt
HelperJS-1.0.dist-info/RECORD
