Metadata-Version: 2.1
Name: HelperJS
Version: 1.0
Summary: Python helper for JS
Home-page: https://github.com/foollingn/helperJS
Author: fool
Author-email: foolnae@gmail.com
Classifier: Programming Language :: Python :: 3
Classifier: License :: OSI Approved :: MIT License
Classifier: Operating System :: OS Independent
Requires-Python: >=3.6
